{
	"Generated": "2026-04-10T17:25:27.561Z",
	"DocumentCount": 13,
	"LunrIndex": {
		"version": "2.3.9",
		"fields": [
			"title",
			"module",
			"group",
			"body"
		],
		"fieldVectors": [
			[
				"title/example_applications/basic/README.md",
				[
					0,
					8.827,
					1,
					8.827,
					2,
					13.098
				]
			],
			[
				"module/example_applications/basic/README.md",
				[
					3,
					5.675
				]
			],
			[
				"group/example_applications/basic/README.md",
				[
					4,
					1.497
				]
			],
			[
				"body/example_applications/basic/README.md",
				[
					0,
					1.493,
					1,
					1.73,
					2,
					2.215,
					5,
					1.431,
					6,
					1.779,
					7,
					2.421,
					8,
					1.431,
					9,
					2.306,
					10,
					2.306,
					11,
					1.431,
					12,
					0.965,
					13,
					1.779,
					14,
					2.753,
					15,
					2.421,
					16,
					0.493,
					17,
					0.644,
					18,
					1.779,
					19,
					1.431,
					20,
					2.753,
					21,
					3.139,
					22,
					2.306,
					23,
					3.139,
					24,
					1.431,
					25,
					1.316,
					26,
					2.306,
					27,
					1.431,
					28,
					1.595,
					29,
					0.792,
					30,
					1.779,
					31,
					0.965,
					32,
					1.431,
					33,
					1.431,
					34,
					2.306,
					35,
					3.139,
					36,
					0.965,
					37,
					2.306,
					38,
					2.306,
					39,
					2.306,
					40,
					0.515,
					41,
					1.595,
					42,
					1.948,
					43,
					1.431,
					44,
					1.779,
					45,
					1.779,
					46,
					2.306,
					47,
					1.779,
					48,
					0.792,
					49,
					2.306,
					50,
					0.965,
					51,
					2.306,
					52,
					1.779,
					53,
					1.779,
					54,
					3.139,
					55,
					1.779,
					56,
					2.306,
					57,
					2.306
				]
			],
			[
				"title/example_applications/basic/advanced-topics.md",
				[
					28,
					12.575,
					58,
					19.087
				]
			],
			[
				"module/example_applications/basic/advanced-topics.md",
				[
					3,
					5.675
				]
			],
			[
				"group/example_applications/basic/advanced-topics.md",
				[
					4,
					1.497
				]
			],
			[
				"body/example_applications/basic/advanced-topics.md",
				[
					0,
					0.943,
					1,
					1.718,
					13,
					2.384,
					14,
					1.738,
					15,
					1.738,
					16,
					0.552,
					17,
					0.63,
					18,
					1.738,
					24,
					1.399,
					25,
					1.062,
					27,
					1.918,
					28,
					1.145,
					32,
					1.399,
					40,
					0.504,
					48,
					0.774,
					58,
					2.72,
					59,
					1.145,
					60,
					2.254,
					61,
					1.399,
					62,
					2.254,
					63,
					2.254,
					64,
					2.254,
					65,
					1.399,
					66,
					2.254,
					67,
					2.254,
					68,
					2.254,
					69,
					3.09,
					70,
					2.254,
					71,
					2.254,
					72,
					2.254,
					73,
					1.399,
					74,
					3.527,
					75,
					2.254,
					76,
					2.254,
					77,
					2.254,
					78,
					1.738,
					79,
					1.738,
					80,
					1.399,
					81,
					1.399,
					82,
					1.738,
					83,
					2.254,
					84,
					2.254,
					85,
					1.738,
					86,
					2.254,
					87,
					2.254,
					88,
					1.738,
					89,
					2.254,
					90,
					3.09,
					91,
					2.254,
					92,
					2.254,
					93,
					2.254,
					94,
					2.254,
					95,
					2.254,
					96,
					2.254,
					97,
					2.254,
					98,
					2.254,
					99,
					2.254,
					100,
					1.918,
					101,
					1.738,
					102,
					3.09,
					103,
					2.254,
					104,
					2.254,
					105,
					2.254,
					106,
					2.254,
					107,
					2.254,
					108,
					1.738
				]
			],
			[
				"title/example_applications/basic/getting-started.md",
				[
					41,
					12.575,
					42,
					15.359
				]
			],
			[
				"module/example_applications/basic/getting-started.md",
				[
					3,
					5.675
				]
			],
			[
				"group/example_applications/basic/getting-started.md",
				[
					4,
					1.497
				]
			],
			[
				"body/example_applications/basic/getting-started.md",
				[
					0,
					0.943,
					1,
					1.759,
					3,
					1.145,
					6,
					1.738,
					8,
					1.399,
					11,
					1.399,
					12,
					0.943,
					16,
					0.606,
					24,
					1.399,
					25,
					1.211,
					27,
					1.918,
					28,
					2.02,
					29,
					0.774,
					30,
					1.738,
					41,
					1.145,
					42,
					1.399,
					44,
					1.738,
					45,
					1.738,
					48,
					0.774,
					53,
					1.738,
					55,
					1.738,
					61,
					1.399,
					78,
					2.384,
					80,
					1.399,
					81,
					1.399,
					82,
					2.384,
					85,
					1.738,
					109,
					2.254,
					110,
					2.254,
					111,
					1.399,
					112,
					2.254,
					113,
					2.254,
					114,
					2.254,
					115,
					2.254,
					116,
					2.254,
					117,
					2.254,
					118,
					2.254,
					119,
					1.145,
					120,
					2.254,
					121,
					1.145,
					122,
					1.145,
					123,
					2.254,
					124,
					2.254,
					125,
					2.254,
					126,
					2.254,
					127,
					2.254,
					128,
					1.145,
					129,
					2.254
				]
			],
			[
				"title/example_applications/bookshop/book-detail.md",
				[
					16,
					2.369,
					130,
					5.14,
					131,
					6.319,
					132,
					7.694
				]
			],
			[
				"module/example_applications/bookshop/book-detail.md",
				[
					133,
					2.495
				]
			],
			[
				"group/example_applications/bookshop/book-detail.md",
				[
					4,
					1.497
				]
			],
			[
				"body/example_applications/bookshop/book-detail.md",
				[
					12,
					1.012,
					16,
					0.525,
					17,
					1.022,
					36,
					1.012,
					40,
					0.54,
					50,
					1.356,
					59,
					1.229,
					73,
					1.501,
					111,
					2.269,
					119,
					1.229,
					121,
					1.229,
					122,
					1.647,
					128,
					1.229,
					130,
					1.172,
					131,
					1.342,
					132,
					1.012,
					134,
					1.113,
					135,
					2.418,
					136,
					1.012,
					137,
					2.418,
					138,
					1.501,
					139,
					1.865,
					140,
					1.012,
					141,
					1.501,
					142,
					1.865,
					143,
					1.229,
					144,
					1.865,
					145,
					2.418,
					146,
					2.5,
					147,
					1.501,
					148,
					2.418,
					149,
					1.501,
					150,
					2.418,
					151,
					2.012,
					152,
					1.865,
					153,
					1.865,
					154,
					1.647,
					155,
					2.012,
					156,
					1.865,
					157,
					1.012,
					158,
					2.82,
					159,
					2.418,
					160,
					2.418,
					161,
					2.418,
					162,
					1.501,
					163,
					2.418,
					164,
					2.418,
					165,
					2.418,
					166,
					2.418
				]
			],
			[
				"title/example_applications/bookshop/book-list.md",
				[
					130,
					5.897,
					134,
					7.249,
					167,
					10.723
				]
			],
			[
				"module/example_applications/bookshop/book-list.md",
				[
					133,
					2.495
				]
			],
			[
				"group/example_applications/bookshop/book-list.md",
				[
					4,
					1.497
				]
			],
			[
				"body/example_applications/bookshop/book-list.md",
				[
					16,
					0.524,
					17,
					0.845,
					25,
					0.75,
					29,
					1.039,
					31,
					0.914,
					36,
					0.914,
					40,
					0.488,
					43,
					1.877,
					50,
					0.914,
					52,
					1.685,
					59,
					1.763,
					65,
					1.356,
					111,
					1.356,
					121,
					1.11,
					122,
					1.537,
					130,
					1.221,
					131,
					1.039,
					132,
					0.914,
					134,
					1.286,
					136,
					0.914,
					138,
					1.356,
					140,
					1.566,
					141,
					1.877,
					143,
					1.998,
					144,
					1.685,
					146,
					2.333,
					147,
					1.356,
					149,
					2.153,
					151,
					2.153,
					153,
					1.685,
					154,
					1.763,
					157,
					0.914,
					158,
					1.685,
					167,
					1.11,
					168,
					3.744,
					169,
					1.685,
					170,
					1.685,
					171,
					2.184,
					172,
					2.184,
					173,
					2.184,
					174,
					2.333,
					175,
					2.184,
					176,
					2.333,
					177,
					2.184,
					178,
					2.184,
					179,
					1.685,
					180,
					1.685,
					181,
					1.685,
					182,
					2.184,
					183,
					2.184,
					184,
					1.356,
					185,
					2.184
				]
			],
			[
				"title/example_applications/bookshop/search-filter.md",
				[
					16,
					2.718,
					29,
					7.249,
					100,
					13.098
				]
			],
			[
				"module/example_applications/bookshop/search-filter.md",
				[
					133,
					2.495
				]
			],
			[
				"group/example_applications/bookshop/search-filter.md",
				[
					4,
					1.497
				]
			],
			[
				"body/example_applications/bookshop/search-filter.md",
				[
					16,
					0.524,
					17,
					0.673,
					19,
					1.494,
					20,
					1.856,
					25,
					0.827,
					29,
					1.397,
					31,
					1.007,
					33,
					1.494,
					40,
					0.538,
					47,
					1.856,
					48,
					0.827,
					61,
					2.005,
					79,
					1.856,
					88,
					1.856,
					100,
					2.005,
					101,
					1.856,
					119,
					1.223,
					122,
					1.642,
					128,
					1.223,
					130,
					1.215,
					131,
					0.827,
					133,
					0.538,
					134,
					1.11,
					140,
					1.007,
					141,
					1.494,
					143,
					2.066,
					147,
					2.005,
					157,
					1.007,
					181,
					1.856,
					184,
					2.005,
					186,
					2.407,
					187,
					1.856,
					188,
					2.407,
					189,
					3.231,
					190,
					2.407,
					191,
					2.407,
					192,
					2.407,
					193,
					2.407,
					194,
					2.407,
					195,
					2.407,
					196,
					2.407,
					197,
					2.407,
					198,
					2.407,
					199,
					2.407,
					200,
					2.407,
					201,
					2.407,
					202,
					2.407,
					203,
					1.856,
					204,
					2.407
				]
			],
			[
				"title/example_applications/bookshop/store.md",
				[
					40,
					5.528,
					136,
					10.351
				]
			],
			[
				"module/example_applications/bookshop/store.md",
				[
					133,
					2.495
				]
			],
			[
				"group/example_applications/bookshop/store.md",
				[
					4,
					1.497
				]
			],
			[
				"body/example_applications/bookshop/store.md",
				[
					12,
					0.864,
					16,
					0.58,
					17,
					0.577,
					19,
					1.283,
					29,
					0.71,
					31,
					0.864,
					36,
					0.864,
					40,
					0.861,
					48,
					0.71,
					50,
					0.864,
					59,
					1.05,
					65,
					1.806,
					119,
					1.05,
					121,
					1.05,
					128,
					1.478,
					130,
					1.147,
					131,
					0.71,
					132,
					1.217,
					134,
					1.157,
					136,
					1.611,
					138,
					1.283,
					139,
					1.594,
					140,
					1.217,
					142,
					1.594,
					143,
					1.05,
					149,
					2.268,
					151,
					2.09,
					152,
					1.594,
					154,
					1.478,
					155,
					1.283,
					156,
					2.244,
					157,
					0.864,
					162,
					1.806,
					167,
					1.05,
					170,
					1.594,
					174,
					1.594,
					176,
					2.244,
					179,
					1.594,
					180,
					1.594,
					184,
					1.283,
					187,
					1.594,
					203,
					1.594,
					205,
					2.066,
					206,
					2.066,
					207,
					2.066,
					208,
					2.909,
					209,
					3.367,
					210,
					2.066,
					211,
					2.066,
					212,
					2.066,
					213,
					2.066,
					214,
					2.066,
					215,
					2.066,
					216,
					2.066,
					217,
					2.066,
					218,
					2.066,
					219,
					2.066,
					220,
					2.066,
					221,
					2.066,
					222,
					2.066,
					223,
					2.066,
					224,
					2.066,
					225,
					2.066
				]
			],
			[
				"title/example_applications/bookshop/welcome.md",
				[
					5,
					15.359,
					133,
					5.528
				]
			],
			[
				"module/example_applications/bookshop/welcome.md",
				[
					133,
					2.495
				]
			],
			[
				"group/example_applications/bookshop/welcome.md",
				[
					4,
					1.497
				]
			],
			[
				"body/example_applications/bookshop/welcome.md",
				[
					0,
					0.854,
					1,
					1.206,
					2,
					1.267,
					5,
					1.79,
					7,
					1.574,
					8,
					1.267,
					11,
					1.267,
					12,
					1.52,
					16,
					0.593,
					17,
					0.57,
					25,
					0.701,
					31,
					0.854,
					32,
					2.076,
					33,
					2.593,
					36,
					1.604,
					40,
					0.644,
					41,
					1.037,
					43,
					1.267,
					48,
					0.701,
					50,
					1.399,
					73,
					1.267,
					80,
					1.267,
					81,
					1.267,
					108,
					2.58,
					130,
					1.016,
					131,
					0.991,
					132,
					0.854,
					133,
					0.644,
					134,
					0.701,
					136,
					1.206,
					140,
					0.854,
					154,
					1.037,
					155,
					1.267,
					157,
					0.854,
					162,
					1.267,
					167,
					1.037,
					169,
					1.574,
					226,
					2.041,
					227,
					2.041,
					228,
					2.041,
					229,
					2.041,
					230,
					2.884,
					231,
					3.345,
					232,
					2.041,
					233,
					2.041,
					234,
					2.041,
					235,
					2.041,
					236,
					2.041,
					237,
					2.884,
					238,
					2.041,
					239,
					3.345,
					240,
					2.041,
					241,
					2.041,
					242,
					2.041,
					243,
					2.884,
					244,
					2.041
				]
			]
		],
		"invertedIndex": [
			[
				"",
				{
					"_index": 16,
					"title": {
						"example_applications/bookshop/book-detail.md": {},
						"example_applications/bookshop/search-filter.md": {}
					},
					"module": {},
					"group": {},
					"body": {
						"example_applications/basic/README.md": {},
						"example_applications/basic/advanced-topics.md": {},
						"example_applications/basic/getting-started.md": {},
						"example_applications/bookshop/book-detail.md": {},
						"example_applications/bookshop/book-list.md": {},
						"example_applications/bookshop/search-filter.md": {},
						"example_applications/bookshop/store.md": {},
						"example_applications/bookshop/welcome.md": {}
					}
				}
			],
			[
				"abov",
				{
					"_index": 182,
					"title": {},
					"module": {},
					"group": {},
					"body": {
						"example_applications/bookshop/book-list.md": {}
					}
				}
			],
			[
				"action",
				{
					"_index": 155,
					"title": {},
					"module": {},
					"group": {},
					"body": {
						"example_applications/bookshop/book-detail.md": {},
						"example_applications/bookshop/store.md": {},
						"example_applications/bookshop/welcome.md": {}
					}
				}
			],
			[
				"activ",
				{
					"_index": 116,
					"title": {},
					"module": {},
					"group": {},
					"body": {
						"example_applications/basic/getting-started.md": {}
					}
				}
			],
			[
				"add",
				{
					"_index": 111,
					"title": {},
					"module": {},
					"group": {},
					"body": {
						"example_applications/basic/getting-started.md": {},
						"example_applications/bookshop/book-detail.md": {},
						"example_applications/bookshop/book-list.md": {}
					}
				}
			],
			[
				"advanc",
				{
					"_index": 58,
					"title": {
						"example_applications/basic/advanced-topics.md": {}
					},
					"module": {},
					"group": {},
					"body": {
						"example_applications/basic/advanced-topics.md": {}
					}
				}
			],
			[
				"again",
				{
					"_index": 185,
					"title": {},
					"module": {},
					"group": {},
					"body": {
						"example_applications/bookshop/book-list.md": {}
					}
				}
			],
			[
				"ai",
				{
					"_index": 102,
					"title": {},
					"module": {},
					"group": {},
					"body": {
						"example_applications/basic/advanced-topics.md": {}
					}
				}
			],
			[
				"algorithm",
				{
					"_index": 200,
					"title": {},
					"module": {},
					"group": {},
					"body": {
						"example_applications/bookshop/search-filter.md": {}
					}
				}
			],
			[
				"alongsid",
				{
					"_index": 227,
					"title": {},
					"module": {},
					"group": {},
					"body": {
						"example_applications/bookshop/welcome.md": {}
					}
				}
			],
			[
				"api",
				{
					"_index": 55,
					"title": {},
					"module": {},
					"group": {},
					"body": {
						"example_applications/basic/README.md": {},
						"example_applications/basic/getting-started.md": {}
					}
				}
			],
			[
				"app",
				{
					"_index": 226,
					"title": {},
					"module": {},
					"group": {},
					"body": {
						"example_applications/bookshop/welcome.md": {}
					}
				}
			],
			[
				"appdata",
				{
					"_index": 72,
					"title": {},
					"module": {},
					"group": {},
					"body": {
						"example_applications/basic/advanced-topics.md": {}
					}
				}
			],
			[
				"applic",
				{
					"_index": 12,
					"title": {},
					"module": {},
					"group": {},
					"body": {
						"example_applications/basic/README.md": {},
						"example_applications/basic/getting-started.md": {},
						"example_applications/bookshop/book-detail.md": {},
						"example_applications/bookshop/store.md": {},
						"example_applications/bookshop/welcome.md": {}
					}
				}
			],
			[
				"architectur",
				{
					"_index": 47,
					"title": {},
					"module": {},
					"group": {},
					"body": {
						"example_applications/basic/README.md": {},
						"example_applications/bookshop/search-filter.md": {}
					}
				}
			],
			[
				"around",
				{
					"_index": 228,
					"title": {},
					"module": {},
					"group": {},
					"body": {
						"example_applications/bookshop/welcome.md": {}
					}
				}
			],
			[
				"assist",
				{
					"_index": 104,
					"title": {},
					"module": {},
					"group": {},
					"body": {
						"example_applications/basic/advanced-topics.md": {}
					}
				}
			],
			[
				"author",
				{
					"_index": 141,
					"title": {},
					"module": {},
					"group": {},
					"body": {
						"example_applications/bookshop/book-detail.md": {},
						"example_applications/bookshop/book-list.md": {},
						"example_applications/bookshop/search-filter.md": {}
					}
				}
			],
			[
				"author(",
				{
					"_index": 172,
					"title": {},
					"module": {},
					"group": {},
					"body": {
						"example_applications/bookshop/book-list.md": {}
					}
				}
			],
			[
				"avail",
				{
					"_index": 154,
					"title": {},
					"module": {},
					"group": {},
					"body": {
						"example_applications/bookshop/book-detail.md": {},
						"example_applications/bookshop/book-list.md": {},
						"example_applications/bookshop/store.md": {},
						"example_applications/bookshop/welcome.md": {}
					}
				}
			],
			[
				"back",
				{
					"_index": 128,
					"title": {},
					"module": {},
					"group": {},
					"body": {
						"example_applications/basic/getting-started.md": {},
						"example_applications/bookshop/book-detail.md": {},
						"example_applications/bookshop/search-filter.md": {},
						"example_applications/bookshop/store.md": {}
					}
				}
			],
			[
				"badg",
				{
					"_index": 144,
					"title": {},
					"module": {},
					"group": {},
					"body": {
						"example_applications/bookshop/book-detail.md": {},
						"example_applications/bookshop/book-list.md": {}
					}
				}
			],
			[
				"base",
				{
					"_index": 81,
					"title": {},
					"module": {},
					"group": {},
					"body": {
						"example_applications/basic/advanced-topics.md": {},
						"example_applications/basic/getting-started.md": {},
						"example_applications/bookshop/welcome.md": {}
					}
				}
			],
			[
				"basic",
				{
					"_index": 3,
					"title": {},
					"module": {
						"example_applications/basic/README.md": {},
						"example_applications/basic/advanced-topics.md": {},
						"example_applications/basic/getting-started.md": {}
					},
					"group": {},
					"body": {
						"example_applications/basic/getting-started.md": {}
					}
				}
			],
			[
				"belong",
				{
					"_index": 173,
					"title": {},
					"module": {},
					"group": {},
					"body": {
						"example_applications/bookshop/book-list.md": {}
					}
				}
			],
			[
				"between",
				{
					"_index": 37,
					"title": {},
					"module": {},
					"group": {},
					"body": {
						"example_applications/basic/README.md": {}
					}
				}
			],
			[
				"block",
				{
					"_index": 21,
					"title": {},
					"module": {},
					"group": {},
					"body": {
						"example_applications/basic/README.md": {}
					}
				}
			],
			[
				"blockquot",
				{
					"_index": 23,
					"title": {},
					"module": {},
					"group": {},
					"body": {
						"example_applications/basic/README.md": {}
					}
				}
			],
			[
				"book",
				{
					"_index": 130,
					"title": {
						"example_applications/bookshop/book-detail.md": {},
						"example_applications/bookshop/book-list.md": {}
					},
					"module": {},
					"group": {},
					"body": {
						"example_applications/bookshop/book-detail.md": {},
						"example_applications/bookshop/book-list.md": {},
						"example_applications/bookshop/search-filter.md": {},
						"example_applications/bookshop/store.md": {},
						"example_applications/bookshop/welcome.md": {}
					}
				}
			],
			[
				"book'",
				{
					"_index": 146,
					"title": {},
					"module": {},
					"group": {},
					"body": {
						"example_applications/bookshop/book-detail.md": {},
						"example_applications/bookshop/book-list.md": {}
					}
				}
			],
			[
				"bookshop",
				{
					"_index": 133,
					"title": {
						"example_applications/bookshop/welcome.md": {}
					},
					"module": {
						"example_applications/bookshop/book-detail.md": {},
						"example_applications/bookshop/book-list.md": {},
						"example_applications/bookshop/search-filter.md": {},
						"example_applications/bookshop/store.md": {},
						"example_applications/bookshop/welcome.md": {}
					},
					"group": {},
					"body": {
						"example_applications/bookshop/search-filter.md": {},
						"example_applications/bookshop/welcome.md": {}
					}
				}
			],
			[
				"brows",
				{
					"_index": 167,
					"title": {
						"example_applications/bookshop/book-list.md": {}
					},
					"module": {},
					"group": {},
					"body": {
						"example_applications/bookshop/book-list.md": {},
						"example_applications/bookshop/store.md": {},
						"example_applications/bookshop/welcome.md": {}
					}
				}
			],
			[
				"browser",
				{
					"_index": 6,
					"title": {},
					"module": {},
					"group": {},
					"body": {
						"example_applications/basic/README.md": {},
						"example_applications/basic/getting-started.md": {}
					}
				}
			],
			[
				"button",
				{
					"_index": 162,
					"title": {},
					"module": {},
					"group": {},
					"body": {
						"example_applications/bookshop/book-detail.md": {},
						"example_applications/bookshop/store.md": {},
						"example_applications/bookshop/welcome.md": {}
					}
				}
			],
			[
				"cach",
				{
					"_index": 74,
					"title": {},
					"module": {},
					"group": {},
					"body": {
						"example_applications/basic/advanced-topics.md": {}
					}
				}
			],
			[
				"call",
				{
					"_index": 112,
					"title": {},
					"module": {},
					"group": {},
					"body": {
						"example_applications/basic/getting-started.md": {}
					}
				}
			],
			[
				"capabl",
				{
					"_index": 57,
					"title": {},
					"module": {},
					"group": {},
					"body": {
						"example_applications/basic/README.md": {}
					}
				}
			],
			[
				"card",
				{
					"_index": 168,
					"title": {},
					"module": {},
					"group": {},
					"body": {
						"example_applications/bookshop/book-list.md": {}
					}
				}
			],
			[
				"cart",
				{
					"_index": 158,
					"title": {},
					"module": {},
					"group": {},
					"body": {
						"example_applications/bookshop/book-detail.md": {},
						"example_applications/bookshop/book-list.md": {}
					}
				}
			],
			[
				"catalog",
				{
					"_index": 134,
					"title": {
						"example_applications/bookshop/book-list.md": {}
					},
					"module": {},
					"group": {},
					"body": {
						"example_applications/bookshop/book-detail.md": {},
						"example_applications/bookshop/book-list.md": {},
						"example_applications/bookshop/search-filter.md": {},
						"example_applications/bookshop/store.md": {},
						"example_applications/bookshop/welcome.md": {}
					}
				}
			],
			[
				"categori",
				{
					"_index": 147,
					"title": {},
					"module": {},
					"group": {},
					"body": {
						"example_applications/bookshop/book-detail.md": {},
						"example_applications/bookshop/book-list.md": {},
						"example_applications/bookshop/search-filter.md": {}
					}
				}
			],
			[
				"chang",
				{
					"_index": 80,
					"title": {},
					"module": {},
					"group": {},
					"body": {
						"example_applications/basic/advanced-topics.md": {},
						"example_applications/basic/getting-started.md": {},
						"example_applications/bookshop/welcome.md": {}
					}
				}
			],
			[
				"check",
				{
					"_index": 223,
					"title": {},
					"module": {},
					"group": {},
					"body": {
						"example_applications/bookshop/store.md": {}
					}
				}
			],
			[
				"checkout",
				{
					"_index": 217,
					"title": {},
					"module": {},
					"group": {},
					"body": {
						"example_applications/bookshop/store.md": {}
					}
				}
			],
			[
				"circl",
				{
					"_index": 232,
					"title": {},
					"module": {},
					"group": {},
					"body": {
						"example_applications/bookshop/welcome.md": {}
					}
				}
			],
			[
				"clear",
				{
					"_index": 76,
					"title": {},
					"module": {},
					"group": {},
					"body": {
						"example_applications/basic/advanced-topics.md": {}
					}
				}
			],
			[
				"click",
				{
					"_index": 36,
					"title": {},
					"module": {},
					"group": {},
					"body": {
						"example_applications/basic/README.md": {},
						"example_applications/bookshop/book-detail.md": {},
						"example_applications/bookshop/book-list.md": {},
						"example_applications/bookshop/store.md": {},
						"example_applications/bookshop/welcome.md": {}
					}
				}
			],
			[
				"code",
				{
					"_index": 20,
					"title": {},
					"module": {},
					"group": {},
					"body": {
						"example_applications/basic/README.md": {},
						"example_applications/bookshop/search-filter.md": {}
					}
				}
			],
			[
				"column",
				{
					"_index": 209,
					"title": {},
					"module": {},
					"group": {},
					"body": {
						"example_applications/bookshop/store.md": {}
					}
				}
			],
			[
				"comput",
				{
					"_index": 195,
					"title": {},
					"module": {},
					"group": {},
					"body": {
						"example_applications/bookshop/search-filter.md": {}
					}
				}
			],
			[
				"concept",
				{
					"_index": 96,
					"title": {},
					"module": {},
					"group": {},
					"body": {
						"example_applications/basic/advanced-topics.md": {}
					}
				}
			],
			[
				"contain",
				{
					"_index": 63,
					"title": {},
					"module": {},
					"group": {},
					"body": {
						"example_applications/basic/advanced-topics.md": {}
					}
				}
			],
			[
				"content",
				{
					"_index": 73,
					"title": {},
					"module": {},
					"group": {},
					"body": {
						"example_applications/basic/advanced-topics.md": {},
						"example_applications/bookshop/book-detail.md": {},
						"example_applications/bookshop/welcome.md": {}
					}
				}
			],
			[
				"contextu",
				{
					"_index": 32,
					"title": {},
					"module": {},
					"group": {},
					"body": {
						"example_applications/basic/README.md": {},
						"example_applications/basic/advanced-topics.md": {},
						"example_applications/bookshop/welcome.md": {}
					}
				}
			],
			[
				"cover",
				{
					"_index": 59,
					"title": {},
					"module": {},
					"group": {},
					"body": {
						"example_applications/basic/advanced-topics.md": {},
						"example_applications/bookshop/book-detail.md": {},
						"example_applications/bookshop/book-list.md": {},
						"example_applications/bookshop/store.md": {}
					}
				}
			],
			[
				"creat",
				{
					"_index": 83,
					"title": {},
					"module": {},
					"group": {},
					"body": {
						"example_applications/basic/advanced-topics.md": {}
					}
				}
			],
			[
				"cs",
				{
					"_index": 198,
					"title": {},
					"module": {},
					"group": {},
					"body": {
						"example_applications/bookshop/search-filter.md": {}
					}
				}
			],
			[
				"current",
				{
					"_index": 174,
					"title": {},
					"module": {},
					"group": {},
					"body": {
						"example_applications/bookshop/book-list.md": {},
						"example_applications/bookshop/store.md": {}
					}
				}
			],
			[
				"custom",
				{
					"_index": 62,
					"title": {},
					"module": {},
					"group": {},
					"body": {
						"example_applications/basic/advanced-topics.md": {}
					}
				}
			],
			[
				"decis",
				{
					"_index": 207,
					"title": {},
					"module": {},
					"group": {},
					"body": {
						"example_applications/bookshop/store.md": {}
					}
				}
			],
			[
				"default",
				{
					"_index": 64,
					"title": {},
					"module": {},
					"group": {},
					"body": {
						"example_applications/basic/advanced-topics.md": {}
					}
				}
			],
			[
				"defin",
				{
					"_index": 114,
					"title": {},
					"module": {},
					"group": {},
					"body": {
						"example_applications/basic/getting-started.md": {}
					}
				}
			],
			[
				"demo",
				{
					"_index": 161,
					"title": {},
					"module": {},
					"group": {},
					"body": {
						"example_applications/bookshop/book-detail.md": {}
					}
				}
			],
			[
				"demonstr",
				{
					"_index": 7,
					"title": {},
					"module": {},
					"group": {},
					"body": {
						"example_applications/basic/README.md": {},
						"example_applications/bookshop/welcome.md": {}
					}
				}
			],
			[
				"descript",
				{
					"_index": 119,
					"title": {},
					"module": {},
					"group": {},
					"body": {
						"example_applications/basic/getting-started.md": {},
						"example_applications/bookshop/book-detail.md": {},
						"example_applications/bookshop/search-filter.md": {},
						"example_applications/bookshop/store.md": {}
					}
				}
			],
			[
				"design",
				{
					"_index": 192,
					"title": {},
					"module": {},
					"group": {},
					"body": {
						"example_applications/bookshop/search-filter.md": {}
					}
				}
			],
			[
				"detach",
				{
					"_index": 107,
					"title": {},
					"module": {},
					"group": {},
					"body": {
						"example_applications/basic/advanced-topics.md": {}
					}
				}
			],
			[
				"detail",
				{
					"_index": 131,
					"title": {
						"example_applications/bookshop/book-detail.md": {}
					},
					"module": {},
					"group": {},
					"body": {
						"example_applications/bookshop/book-detail.md": {},
						"example_applications/bookshop/book-list.md": {},
						"example_applications/bookshop/search-filter.md": {},
						"example_applications/bookshop/store.md": {},
						"example_applications/bookshop/welcome.md": {}
					}
				}
			],
			[
				"display",
				{
					"_index": 121,
					"title": {},
					"module": {},
					"group": {},
					"body": {
						"example_applications/basic/getting-started.md": {},
						"example_applications/bookshop/book-detail.md": {},
						"example_applications/bookshop/book-list.md": {},
						"example_applications/bookshop/store.md": {}
					}
				}
			],
			[
				"distribut",
				{
					"_index": 193,
					"title": {},
					"module": {},
					"group": {},
					"body": {
						"example_applications/bookshop/search-filter.md": {}
					}
				}
			],
			[
				"doc",
				{
					"_index": 78,
					"title": {},
					"module": {},
					"group": {},
					"body": {
						"example_applications/basic/advanced-topics.md": {},
						"example_applications/basic/getting-started.md": {}
					}
				}
			],
			[
				"dock",
				{
					"_index": 105,
					"title": {},
					"module": {},
					"group": {},
					"body": {
						"example_applications/basic/advanced-topics.md": {}
					}
				}
			],
			[
				"document",
				{
					"_index": 1,
					"title": {
						"example_applications/basic/README.md": {}
					},
					"module": {},
					"group": {},
					"body": {
						"example_applications/basic/README.md": {},
						"example_applications/basic/advanced-topics.md": {},
						"example_applications/basic/getting-started.md": {},
						"example_applications/bookshop/welcome.md": {}
					}
				}
			],
			[
				"dropdown",
				{
					"_index": 181,
					"title": {},
					"module": {},
					"group": {},
					"body": {
						"example_applications/bookshop/book-list.md": {},
						"example_applications/bookshop/search-filter.md": {}
					}
				}
			],
			[
				"e.g",
				{
					"_index": 77,
					"title": {},
					"module": {},
					"group": {},
					"body": {
						"example_applications/basic/advanced-topics.md": {}
					}
				}
			],
			[
				"each",
				{
					"_index": 169,
					"title": {},
					"module": {},
					"group": {},
					"body": {
						"example_applications/bookshop/book-list.md": {},
						"example_applications/bookshop/welcome.md": {}
					}
				}
			],
			[
				"edit",
				{
					"_index": 90,
					"title": {},
					"module": {},
					"group": {},
					"body": {
						"example_applications/basic/advanced-topics.md": {}
					}
				}
			],
			[
				"element",
				{
					"_index": 66,
					"title": {},
					"module": {},
					"group": {},
					"body": {
						"example_applications/basic/advanced-topics.md": {}
					}
				}
			],
			[
				"embed",
				{
					"_index": 8,
					"title": {},
					"module": {},
					"group": {},
					"body": {
						"example_applications/basic/README.md": {},
						"example_applications/basic/getting-started.md": {},
						"example_applications/bookshop/welcome.md": {}
					}
				}
			],
			[
				"engin",
				{
					"_index": 190,
					"title": {},
					"module": {},
					"group": {},
					"body": {
						"example_applications/bookshop/search-filter.md": {}
					}
				}
			],
			[
				"exampl",
				{
					"_index": 2,
					"title": {
						"example_applications/basic/README.md": {}
					},
					"module": {},
					"group": {},
					"body": {
						"example_applications/basic/README.md": {},
						"example_applications/bookshop/welcome.md": {}
					}
				}
			],
			[
				"example_appl",
				{
					"_index": 4,
					"title": {},
					"module": {},
					"group": {
						"example_applications/basic/README.md": {},
						"example_applications/basic/advanced-topics.md": {},
						"example_applications/basic/getting-started.md": {},
						"example_applications/bookshop/book-detail.md": {},
						"example_applications/bookshop/book-list.md": {},
						"example_applications/bookshop/search-filter.md": {},
						"example_applications/bookshop/store.md": {},
						"example_applications/bookshop/welcome.md": {}
					},
					"body": {}
				}
			],
			[
				"f1",
				{
					"_index": 231,
					"title": {},
					"module": {},
					"group": {},
					"body": {
						"example_applications/bookshop/welcome.md": {}
					}
				}
			],
			[
				"featur",
				{
					"_index": 13,
					"title": {},
					"module": {},
					"group": {},
					"body": {
						"example_applications/basic/README.md": {},
						"example_applications/basic/advanced-topics.md": {}
					}
				}
			],
			[
				"fee",
				{
					"_index": 216,
					"title": {},
					"module": {},
					"group": {},
					"body": {
						"example_applications/bookshop/store.md": {}
					}
				}
			],
			[
				"file",
				{
					"_index": 115,
					"title": {},
					"module": {},
					"group": {},
					"body": {
						"example_applications/basic/getting-started.md": {}
					}
				}
			],
			[
				"filter",
				{
					"_index": 29,
					"title": {
						"example_applications/bookshop/search-filter.md": {}
					},
					"module": {},
					"group": {},
					"body": {
						"example_applications/basic/README.md": {},
						"example_applications/basic/getting-started.md": {},
						"example_applications/bookshop/book-list.md": {},
						"example_applications/bookshop/search-filter.md": {},
						"example_applications/bookshop/store.md": {}
					}
				}
			],
			[
				"final",
				{
					"_index": 214,
					"title": {},
					"module": {},
					"group": {},
					"body": {
						"example_applications/bookshop/store.md": {}
					}
				}
			],
			[
				"find",
				{
					"_index": 186,
					"title": {},
					"module": {},
					"group": {},
					"body": {
						"example_applications/bookshop/search-filter.md": {}
					}
				}
			],
			[
				"first",
				{
					"_index": 75,
					"title": {},
					"module": {},
					"group": {},
					"body": {
						"example_applications/basic/advanced-topics.md": {}
					}
				}
			],
			[
				"foundat",
				{
					"_index": 197,
					"title": {},
					"module": {},
					"group": {},
					"body": {
						"example_applications/bookshop/search-filter.md": {}
					}
				}
			],
			[
				"full",
				{
					"_index": 17,
					"title": {},
					"module": {},
					"group": {},
					"body": {
						"example_applications/basic/README.md": {},
						"example_applications/basic/advanced-topics.md": {},
						"example_applications/bookshop/book-detail.md": {},
						"example_applications/bookshop/book-list.md": {},
						"example_applications/bookshop/search-filter.md": {},
						"example_applications/bookshop/store.md": {},
						"example_applications/bookshop/welcome.md": {}
					}
				}
			],
			[
				"futur",
				{
					"_index": 88,
					"title": {},
					"module": {},
					"group": {},
					"body": {
						"example_applications/basic/advanced-topics.md": {},
						"example_applications/bookshop/search-filter.md": {}
					}
				}
			],
			[
				"genr",
				{
					"_index": 143,
					"title": {},
					"module": {},
					"group": {},
					"body": {
						"example_applications/bookshop/book-detail.md": {},
						"example_applications/bookshop/book-list.md": {},
						"example_applications/bookshop/search-filter.md": {},
						"example_applications/bookshop/store.md": {}
					}
				}
			],
			[
				"get",
				{
					"_index": 41,
					"title": {
						"example_applications/basic/getting-started.md": {}
					},
					"module": {},
					"group": {},
					"body": {
						"example_applications/basic/README.md": {},
						"example_applications/basic/getting-started.md": {},
						"example_applications/bookshop/welcome.md": {}
					}
				}
			],
			[
				"go",
				{
					"_index": 123,
					"title": {},
					"module": {},
					"group": {},
					"body": {
						"example_applications/basic/getting-started.md": {}
					}
				}
			],
			[
				"guid",
				{
					"_index": 44,
					"title": {},
					"module": {},
					"group": {},
					"body": {
						"example_applications/basic/README.md": {},
						"example_applications/basic/getting-started.md": {}
					}
				}
			],
			[
				"header",
				{
					"_index": 242,
					"title": {},
					"module": {},
					"group": {},
					"body": {
						"example_applications/bookshop/welcome.md": {}
					}
				}
			],
			[
				"help",
				{
					"_index": 33,
					"title": {},
					"module": {},
					"group": {},
					"body": {
						"example_applications/basic/README.md": {},
						"example_applications/bookshop/search-filter.md": {},
						"example_applications/bookshop/welcome.md": {}
					}
				}
			],
			[
				"here",
				{
					"_index": 56,
					"title": {},
					"module": {},
					"group": {},
					"body": {
						"example_applications/basic/README.md": {}
					}
				}
			],
			[
				"hidden",
				{
					"_index": 215,
					"title": {},
					"module": {},
					"group": {},
					"body": {
						"example_applications/bookshop/store.md": {}
					}
				}
			],
			[
				"hierarch",
				{
					"_index": 26,
					"title": {},
					"module": {},
					"group": {},
					"body": {
						"example_applications/basic/README.md": {}
					}
				}
			],
			[
				"home",
				{
					"_index": 129,
					"title": {},
					"module": {},
					"group": {},
					"body": {
						"example_applications/basic/getting-started.md": {}
					}
				}
			],
			[
				"hover",
				{
					"_index": 94,
					"title": {},
					"module": {},
					"group": {},
					"body": {
						"example_applications/basic/advanced-topics.md": {}
					}
				}
			],
			[
				"icon",
				{
					"_index": 233,
					"title": {},
					"module": {},
					"group": {},
					"body": {
						"example_applications/bookshop/welcome.md": {}
					}
				}
			],
			[
				"id",
				{
					"_index": 67,
					"title": {},
					"module": {},
					"group": {},
					"body": {
						"example_applications/basic/advanced-topics.md": {}
					}
				}
			],
			[
				"imag",
				{
					"_index": 138,
					"title": {},
					"module": {},
					"group": {},
					"body": {
						"example_applications/bookshop/book-detail.md": {},
						"example_applications/bookshop/book-list.md": {},
						"example_applications/bookshop/store.md": {}
					}
				}
			],
			[
				"includ",
				{
					"_index": 19,
					"title": {},
					"module": {},
					"group": {},
					"body": {
						"example_applications/basic/README.md": {},
						"example_applications/bookshop/search-filter.md": {},
						"example_applications/bookshop/store.md": {}
					}
				}
			],
			[
				"indic",
				{
					"_index": 145,
					"title": {},
					"module": {},
					"group": {},
					"body": {
						"example_applications/bookshop/book-detail.md": {}
					}
				}
			],
			[
				"inform",
				{
					"_index": 170,
					"title": {},
					"module": {},
					"group": {},
					"body": {
						"example_applications/bookshop/book-list.md": {},
						"example_applications/bookshop/store.md": {}
					}
				}
			],
			[
				"initi",
				{
					"_index": 120,
					"title": {},
					"module": {},
					"group": {},
					"body": {
						"example_applications/basic/getting-started.md": {}
					}
				}
			],
			[
				"inlin",
				{
					"_index": 0,
					"title": {
						"example_applications/basic/README.md": {}
					},
					"module": {},
					"group": {},
					"body": {
						"example_applications/basic/README.md": {},
						"example_applications/basic/advanced-topics.md": {},
						"example_applications/basic/getting-started.md": {},
						"example_applications/bookshop/welcome.md": {}
					}
				}
			],
			[
				"insid",
				{
					"_index": 10,
					"title": {},
					"module": {},
					"group": {},
					"body": {
						"example_applications/basic/README.md": {}
					}
				}
			],
			[
				"instal",
				{
					"_index": 110,
					"title": {},
					"module": {},
					"group": {},
					"body": {
						"example_applications/basic/getting-started.md": {}
					}
				}
			],
			[
				"instanc",
				{
					"_index": 85,
					"title": {},
					"module": {},
					"group": {},
					"body": {
						"example_applications/basic/advanced-topics.md": {},
						"example_applications/basic/getting-started.md": {}
					}
				}
			],
			[
				"instantli",
				{
					"_index": 202,
					"title": {},
					"module": {},
					"group": {},
					"body": {
						"example_applications/bookshop/search-filter.md": {}
					}
				}
			],
			[
				"instruct",
				{
					"_index": 46,
					"title": {},
					"module": {},
					"group": {},
					"body": {
						"example_applications/basic/README.md": {}
					}
				}
			],
			[
				"integr",
				{
					"_index": 103,
					"title": {},
					"module": {},
					"group": {},
					"body": {
						"example_applications/basic/advanced-topics.md": {}
					}
				}
			],
			[
				"interact",
				{
					"_index": 52,
					"title": {},
					"module": {},
					"group": {},
					"body": {
						"example_applications/basic/README.md": {},
						"example_applications/bookshop/book-list.md": {}
					}
				}
			],
			[
				"intern",
				{
					"_index": 34,
					"title": {},
					"module": {},
					"group": {},
					"body": {
						"example_applications/basic/README.md": {}
					}
				}
			],
			[
				"item",
				{
					"_index": 160,
					"title": {},
					"module": {},
					"group": {},
					"body": {
						"example_applications/bookshop/book-detail.md": {}
					}
				}
			],
			[
				"key",
				{
					"_index": 244,
					"title": {},
					"module": {},
					"group": {},
					"body": {
						"example_applications/bookshop/welcome.md": {}
					}
				}
			],
			[
				"languag",
				{
					"_index": 99,
					"title": {},
					"module": {},
					"group": {},
					"body": {
						"example_applications/basic/advanced-topics.md": {}
					}
				}
			],
			[
				"larg",
				{
					"_index": 137,
					"title": {},
					"module": {},
					"group": {},
					"body": {
						"example_applications/bookshop/book-detail.md": {}
					}
				}
			],
			[
				"later",
				{
					"_index": 224,
					"title": {},
					"module": {},
					"group": {},
					"body": {
						"example_applications/bookshop/store.md": {}
					}
				}
			],
			[
				"layout",
				{
					"_index": 65,
					"title": {},
					"module": {},
					"group": {},
					"body": {
						"example_applications/basic/advanced-topics.md": {},
						"example_applications/bookshop/book-list.md": {},
						"example_applications/bookshop/store.md": {}
					}
				}
			],
			[
				"leav",
				{
					"_index": 39,
					"title": {},
					"module": {},
					"group": {},
					"body": {
						"example_applications/basic/README.md": {}
					}
				}
			],
			[
				"left",
				{
					"_index": 139,
					"title": {},
					"module": {},
					"group": {},
					"body": {
						"example_applications/bookshop/book-detail.md": {},
						"example_applications/bookshop/store.md": {}
					}
				}
			],
			[
				"let",
				{
					"_index": 188,
					"title": {},
					"module": {},
					"group": {},
					"body": {
						"example_applications/bookshop/search-filter.md": {}
					}
				}
			],
			[
				"link",
				{
					"_index": 35,
					"title": {},
					"module": {},
					"group": {},
					"body": {
						"example_applications/basic/README.md": {}
					}
				}
			],
			[
				"list",
				{
					"_index": 157,
					"title": {},
					"module": {},
					"group": {},
					"body": {
						"example_applications/bookshop/book-detail.md": {},
						"example_applications/bookshop/book-list.md": {},
						"example_applications/bookshop/search-filter.md": {},
						"example_applications/bookshop/store.md": {},
						"example_applications/bookshop/welcome.md": {}
					}
				}
			],
			[
				"load",
				{
					"_index": 27,
					"title": {},
					"module": {},
					"group": {},
					"body": {
						"example_applications/basic/README.md": {},
						"example_applications/basic/advanced-topics.md": {},
						"example_applications/basic/getting-started.md": {}
					}
				}
			],
			[
				"local",
				{
					"_index": 97,
					"title": {},
					"module": {},
					"group": {},
					"body": {
						"example_applications/basic/advanced-topics.md": {}
					}
				}
			],
			[
				"make",
				{
					"_index": 206,
					"title": {},
					"module": {},
					"group": {},
					"body": {
						"example_applications/bookshop/store.md": {}
					}
				}
			],
			[
				"manag",
				{
					"_index": 49,
					"title": {},
					"module": {},
					"group": {},
					"body": {
						"example_applications/basic/README.md": {}
					}
				}
			],
			[
				"markdown",
				{
					"_index": 14,
					"title": {},
					"module": {},
					"group": {},
					"body": {
						"example_applications/basic/README.md": {},
						"example_applications/basic/advanced-topics.md": {}
					}
				}
			],
			[
				"mean",
				{
					"_index": 220,
					"title": {},
					"module": {},
					"group": {},
					"body": {
						"example_applications/bookshop/store.md": {}
					}
				}
			],
			[
				"metadata",
				{
					"_index": 210,
					"title": {},
					"module": {},
					"group": {},
					"body": {
						"example_applications/bookshop/store.md": {}
					}
				}
			],
			[
				"method",
				{
					"_index": 118,
					"title": {},
					"module": {},
					"group": {},
					"body": {
						"example_applications/basic/getting-started.md": {}
					}
				}
			],
			[
				"mode",
				{
					"_index": 91,
					"title": {},
					"module": {},
					"group": {},
					"body": {
						"example_applications/basic/advanced-topics.md": {}
					}
				}
			],
			[
				"multi",
				{
					"_index": 98,
					"title": {},
					"module": {},
					"group": {},
					"body": {
						"example_applications/basic/advanced-topics.md": {}
					}
				}
			],
			[
				"narrow",
				{
					"_index": 183,
					"title": {},
					"module": {},
					"group": {},
					"body": {
						"example_applications/bookshop/book-list.md": {}
					}
				}
			],
			[
				"navig",
				{
					"_index": 25,
					"title": {},
					"module": {},
					"group": {},
					"body": {
						"example_applications/basic/README.md": {},
						"example_applications/basic/advanced-topics.md": {},
						"example_applications/basic/getting-started.md": {},
						"example_applications/bookshop/book-list.md": {},
						"example_applications/bookshop/search-filter.md": {},
						"example_applications/bookshop/welcome.md": {}
					}
				}
			],
			[
				"need",
				{
					"_index": 205,
					"title": {},
					"module": {},
					"group": {},
					"body": {
						"example_applications/bookshop/store.md": {}
					}
				}
			],
			[
				"new",
				{
					"_index": 84,
					"title": {},
					"module": {},
					"group": {},
					"body": {
						"example_applications/basic/advanced-topics.md": {}
					}
				}
			],
			[
				"next",
				{
					"_index": 241,
					"title": {},
					"module": {},
					"group": {},
					"body": {
						"example_applications/bookshop/welcome.md": {}
					}
				}
			],
			[
				"on",
				{
					"_index": 218,
					"title": {},
					"module": {},
					"group": {},
					"body": {
						"example_applications/bookshop/store.md": {}
					}
				}
			],
			[
				"open",
				{
					"_index": 243,
					"title": {},
					"module": {},
					"group": {},
					"body": {
						"example_applications/bookshop/welcome.md": {}
					}
				}
			],
			[
				"option",
				{
					"_index": 229,
					"title": {},
					"module": {},
					"group": {},
					"body": {
						"example_applications/bookshop/welcome.md": {}
					}
				}
			],
			[
				"out",
				{
					"_index": 176,
					"title": {},
					"module": {},
					"group": {},
					"body": {
						"example_applications/bookshop/book-list.md": {},
						"example_applications/bookshop/store.md": {}
					}
				}
			],
			[
				"overrid",
				{
					"_index": 68,
					"title": {},
					"module": {},
					"group": {},
					"body": {
						"example_applications/basic/advanced-topics.md": {}
					}
				}
			],
			[
				"page",
				{
					"_index": 40,
					"title": {
						"example_applications/bookshop/store.md": {}
					},
					"module": {},
					"group": {},
					"body": {
						"example_applications/basic/README.md": {},
						"example_applications/basic/advanced-topics.md": {},
						"example_applications/bookshop/book-detail.md": {},
						"example_applications/bookshop/book-list.md": {},
						"example_applications/bookshop/search-filter.md": {},
						"example_applications/bookshop/store.md": {},
						"example_applications/bookshop/welcome.md": {}
					}
				}
			],
			[
				"panel",
				{
					"_index": 108,
					"title": {},
					"module": {},
					"group": {},
					"body": {
						"example_applications/basic/advanced-topics.md": {},
						"example_applications/bookshop/welcome.md": {}
					}
				}
			],
			[
				"part",
				{
					"_index": 238,
					"title": {},
					"module": {},
					"group": {},
					"body": {
						"example_applications/bookshop/welcome.md": {}
					}
				}
			],
			[
				"path",
				{
					"_index": 127,
					"title": {},
					"module": {},
					"group": {},
					"body": {
						"example_applications/basic/getting-started.md": {}
					}
				}
			],
			[
				"period",
				{
					"_index": 222,
					"title": {},
					"module": {},
					"group": {},
					"body": {
						"example_applications/bookshop/store.md": {}
					}
				}
			],
			[
				"pict",
				{
					"_index": 11,
					"title": {},
					"module": {},
					"group": {},
					"body": {
						"example_applications/basic/README.md": {},
						"example_applications/basic/getting-started.md": {},
						"example_applications/bookshop/welcome.md": {}
					}
				}
			],
			[
				"place",
				{
					"_index": 92,
					"title": {},
					"module": {},
					"group": {},
					"body": {
						"example_applications/basic/advanced-topics.md": {}
					}
				}
			],
			[
				"plan",
				{
					"_index": 87,
					"title": {},
					"module": {},
					"group": {},
					"body": {
						"example_applications/basic/advanced-topics.md": {}
					}
				}
			],
			[
				"practic",
				{
					"_index": 191,
					"title": {},
					"module": {},
					"group": {},
					"body": {
						"example_applications/bookshop/search-filter.md": {}
					}
				}
			],
			[
				"preserv",
				{
					"_index": 203,
					"title": {},
					"module": {},
					"group": {},
					"body": {
						"example_applications/bookshop/search-filter.md": {},
						"example_applications/bookshop/store.md": {}
					}
				}
			],
			[
				"press",
				{
					"_index": 230,
					"title": {},
					"module": {},
					"group": {},
					"body": {
						"example_applications/bookshop/welcome.md": {}
					}
				}
			],
			[
				"previou",
				{
					"_index": 124,
					"title": {},
					"module": {},
					"group": {},
					"body": {
						"example_applications/basic/getting-started.md": {}
					}
				}
			],
			[
				"price",
				{
					"_index": 149,
					"title": {},
					"module": {},
					"group": {},
					"body": {
						"example_applications/bookshop/book-detail.md": {},
						"example_applications/bookshop/book-list.md": {},
						"example_applications/bookshop/store.md": {}
					}
				}
			],
			[
				"process",
				{
					"_index": 164,
					"title": {},
					"module": {},
					"group": {},
					"body": {
						"example_applications/bookshop/book-detail.md": {}
					}
				}
			],
			[
				"programmat",
				{
					"_index": 69,
					"title": {},
					"module": {},
					"group": {},
					"body": {
						"example_applications/basic/advanced-topics.md": {}
					}
				}
			],
			[
				"promin",
				{
					"_index": 150,
					"title": {},
					"module": {},
					"group": {},
					"body": {
						"example_applications/bookshop/book-detail.md": {}
					}
				}
			],
			[
				"provid",
				{
					"_index": 48,
					"title": {},
					"module": {},
					"group": {},
					"body": {
						"example_applications/basic/README.md": {},
						"example_applications/basic/advanced-topics.md": {},
						"example_applications/basic/getting-started.md": {},
						"example_applications/bookshop/search-filter.md": {},
						"example_applications/bookshop/store.md": {},
						"example_applications/bookshop/welcome.md": {}
					}
				}
			],
			[
				"purchas",
				{
					"_index": 132,
					"title": {
						"example_applications/bookshop/book-detail.md": {}
					},
					"module": {},
					"group": {},
					"body": {
						"example_applications/bookshop/book-detail.md": {},
						"example_applications/bookshop/book-list.md": {},
						"example_applications/bookshop/store.md": {},
						"example_applications/bookshop/welcome.md": {}
					}
				}
			],
			[
				"quick",
				{
					"_index": 234,
					"title": {},
					"module": {},
					"group": {},
					"body": {
						"example_applications/bookshop/welcome.md": {}
					}
				}
			],
			[
				"real",
				{
					"_index": 165,
					"title": {},
					"module": {},
					"group": {},
					"body": {
						"example_applications/bookshop/book-detail.md": {}
					}
				}
			],
			[
				"red",
				{
					"_index": 177,
					"title": {},
					"module": {},
					"group": {},
					"body": {
						"example_applications/bookshop/book-list.md": {}
					}
				}
			],
			[
				"refer",
				{
					"_index": 117,
					"title": {},
					"module": {},
					"group": {},
					"body": {
						"example_applications/basic/getting-started.md": {}
					}
				}
			],
			[
				"releas",
				{
					"_index": 89,
					"title": {},
					"module": {},
					"group": {},
					"body": {
						"example_applications/basic/advanced-topics.md": {}
					}
				}
			],
			[
				"render",
				{
					"_index": 15,
					"title": {},
					"module": {},
					"group": {},
					"body": {
						"example_applications/basic/README.md": {},
						"example_applications/basic/advanced-topics.md": {}
					}
				}
			],
			[
				"resiz",
				{
					"_index": 106,
					"title": {},
					"module": {},
					"group": {},
					"body": {
						"example_applications/basic/advanced-topics.md": {}
					}
				}
			],
			[
				"restock",
				{
					"_index": 221,
					"title": {},
					"module": {},
					"group": {},
					"body": {
						"example_applications/bookshop/store.md": {}
					}
				}
			],
			[
				"retail",
				{
					"_index": 175,
					"title": {},
					"module": {},
					"group": {},
					"body": {
						"example_applications/bookshop/book-list.md": {}
					}
				}
			],
			[
				"return",
				{
					"_index": 156,
					"title": {},
					"module": {},
					"group": {},
					"body": {
						"example_applications/bookshop/book-detail.md": {},
						"example_applications/bookshop/store.md": {}
					}
				}
			],
			[
				"right",
				{
					"_index": 142,
					"title": {},
					"module": {},
					"group": {},
					"body": {
						"example_applications/bookshop/book-detail.md": {},
						"example_applications/bookshop/store.md": {}
					}
				}
			],
			[
				"root",
				{
					"_index": 125,
					"title": {},
					"module": {},
					"group": {},
					"body": {
						"example_applications/basic/getting-started.md": {}
					}
				}
			],
			[
				"scalabl",
				{
					"_index": 194,
					"title": {},
					"module": {},
					"group": {},
					"body": {
						"example_applications/bookshop/search-filter.md": {}
					}
				}
			],
			[
				"scienc",
				{
					"_index": 196,
					"title": {},
					"module": {},
					"group": {},
					"body": {
						"example_applications/bookshop/search-filter.md": {}
					}
				}
			],
			[
				"scope",
				{
					"_index": 30,
					"title": {},
					"module": {},
					"group": {},
					"body": {
						"example_applications/basic/README.md": {},
						"example_applications/basic/getting-started.md": {}
					}
				}
			],
			[
				"search",
				{
					"_index": 100,
					"title": {
						"example_applications/bookshop/search-filter.md": {}
					},
					"module": {},
					"group": {},
					"body": {
						"example_applications/basic/advanced-topics.md": {},
						"example_applications/bookshop/search-filter.md": {}
					}
				}
			],
			[
				"section",
				{
					"_index": 239,
					"title": {},
					"module": {},
					"group": {},
					"body": {
						"example_applications/bookshop/welcome.md": {}
					}
				}
			],
			[
				"see",
				{
					"_index": 43,
					"title": {},
					"module": {},
					"group": {},
					"body": {
						"example_applications/basic/README.md": {},
						"example_applications/bookshop/book-list.md": {},
						"example_applications/bookshop/welcome.md": {}
					}
				}
			],
			[
				"select",
				{
					"_index": 184,
					"title": {},
					"module": {},
					"group": {},
					"body": {
						"example_applications/bookshop/book-list.md": {},
						"example_applications/bookshop/search-filter.md": {},
						"example_applications/bookshop/store.md": {}
					}
				}
			],
			[
				"set",
				{
					"_index": 70,
					"title": {},
					"module": {},
					"group": {},
					"body": {
						"example_applications/basic/advanced-topics.md": {}
					}
				}
			],
			[
				"setup",
				{
					"_index": 45,
					"title": {},
					"module": {},
					"group": {},
					"body": {
						"example_applications/basic/README.md": {},
						"example_applications/basic/getting-started.md": {}
					}
				}
			],
			[
				"shop",
				{
					"_index": 159,
					"title": {},
					"module": {},
					"group": {},
					"body": {
						"example_applications/bookshop/book-detail.md": {}
					}
				}
			],
			[
				"show",
				{
					"_index": 122,
					"title": {},
					"module": {},
					"group": {},
					"body": {
						"example_applications/basic/getting-started.md": {},
						"example_applications/bookshop/book-detail.md": {},
						"example_applications/bookshop/book-list.md": {},
						"example_applications/bookshop/search-filter.md": {}
					}
				}
			],
			[
				"shown",
				{
					"_index": 213,
					"title": {},
					"module": {},
					"group": {},
					"body": {
						"example_applications/bookshop/store.md": {}
					}
				}
			],
			[
				"sidebar",
				{
					"_index": 24,
					"title": {},
					"module": {},
					"group": {},
					"body": {
						"example_applications/basic/README.md": {},
						"example_applications/basic/advanced-topics.md": {},
						"example_applications/basic/getting-started.md": {}
					}
				}
			],
			[
				"similar",
				{
					"_index": 225,
					"title": {},
					"module": {},
					"group": {},
					"body": {
						"example_applications/bookshop/store.md": {}
					}
				}
			],
			[
				"simpl",
				{
					"_index": 54,
					"title": {},
					"module": {},
					"group": {},
					"body": {
						"example_applications/basic/README.md": {}
					}
				}
			],
			[
				"simul",
				{
					"_index": 163,
					"title": {},
					"module": {},
					"group": {},
					"body": {
						"example_applications/bookshop/book-detail.md": {}
					}
				}
			],
			[
				"small",
				{
					"_index": 240,
					"title": {},
					"module": {},
					"group": {},
					"body": {
						"example_applications/bookshop/welcome.md": {}
					}
				}
			],
			[
				"softwar",
				{
					"_index": 189,
					"title": {},
					"module": {},
					"group": {},
					"body": {
						"example_applications/bookshop/search-filter.md": {}
					}
				}
			],
			[
				"specif",
				{
					"_index": 31,
					"title": {},
					"module": {},
					"group": {},
					"body": {
						"example_applications/basic/README.md": {},
						"example_applications/bookshop/book-list.md": {},
						"example_applications/bookshop/search-filter.md": {},
						"example_applications/bookshop/store.md": {},
						"example_applications/bookshop/welcome.md": {}
					}
				}
			],
			[
				"start",
				{
					"_index": 42,
					"title": {
						"example_applications/basic/getting-started.md": {}
					},
					"module": {},
					"group": {},
					"body": {
						"example_applications/basic/README.md": {},
						"example_applications/basic/getting-started.md": {}
					}
				}
			],
			[
				"state",
				{
					"_index": 51,
					"title": {},
					"module": {},
					"group": {},
					"body": {
						"example_applications/basic/README.md": {}
					}
				}
			],
			[
				"statu",
				{
					"_index": 152,
					"title": {},
					"module": {},
					"group": {},
					"body": {
						"example_applications/bookshop/book-detail.md": {},
						"example_applications/bookshop/store.md": {}
					}
				}
			],
			[
				"status",
				{
					"_index": 219,
					"title": {},
					"module": {},
					"group": {},
					"body": {
						"example_applications/bookshop/store.md": {}
					}
				}
			],
			[
				"still",
				{
					"_index": 178,
					"title": {},
					"module": {},
					"group": {},
					"body": {
						"example_applications/bookshop/book-list.md": {}
					}
				}
			],
			[
				"stock",
				{
					"_index": 151,
					"title": {},
					"module": {},
					"group": {},
					"body": {
						"example_applications/bookshop/book-detail.md": {},
						"example_applications/bookshop/book-list.md": {},
						"example_applications/bookshop/store.md": {}
					}
				}
			],
			[
				"store",
				{
					"_index": 136,
					"title": {
						"example_applications/bookshop/store.md": {}
					},
					"module": {},
					"group": {},
					"body": {
						"example_applications/bookshop/book-detail.md": {},
						"example_applications/bookshop/book-list.md": {},
						"example_applications/bookshop/store.md": {},
						"example_applications/bookshop/welcome.md": {}
					}
				}
			],
			[
				"subset",
				{
					"_index": 113,
					"title": {},
					"module": {},
					"group": {},
					"body": {
						"example_applications/basic/getting-started.md": {}
					}
				}
			],
			[
				"summari",
				{
					"_index": 148,
					"title": {},
					"module": {},
					"group": {},
					"body": {
						"example_applications/bookshop/book-detail.md": {}
					}
				}
			],
			[
				"support",
				{
					"_index": 18,
					"title": {},
					"module": {},
					"group": {},
					"body": {
						"example_applications/basic/README.md": {},
						"example_applications/basic/advanced-topics.md": {}
					}
				}
			],
			[
				"system",
				{
					"_index": 61,
					"title": {},
					"module": {},
					"group": {},
					"body": {
						"example_applications/basic/advanced-topics.md": {},
						"example_applications/basic/getting-started.md": {},
						"example_applications/bookshop/search-filter.md": {}
					}
				}
			],
			[
				"tabl",
				{
					"_index": 22,
					"title": {},
					"module": {},
					"group": {},
					"body": {
						"example_applications/basic/README.md": {}
					}
				}
			],
			[
				"taken",
				{
					"_index": 135,
					"title": {},
					"module": {},
					"group": {},
					"body": {
						"example_applications/bookshop/book-detail.md": {}
					}
				}
			],
			[
				"tax",
				{
					"_index": 212,
					"title": {},
					"module": {},
					"group": {},
					"body": {
						"example_applications/bookshop/store.md": {}
					}
				}
			],
			[
				"term",
				{
					"_index": 95,
					"title": {},
					"module": {},
					"group": {},
					"body": {
						"example_applications/basic/advanced-topics.md": {}
					}
				}
			],
			[
				"text",
				{
					"_index": 101,
					"title": {},
					"module": {},
					"group": {},
					"body": {
						"example_applications/basic/advanced-topics.md": {},
						"example_applications/bookshop/search-filter.md": {}
					}
				}
			],
			[
				"theori",
				{
					"_index": 199,
					"title": {},
					"module": {},
					"group": {},
					"body": {
						"example_applications/bookshop/search-filter.md": {}
					}
				}
			],
			[
				"through",
				{
					"_index": 53,
					"title": {},
					"module": {},
					"group": {},
					"body": {
						"example_applications/basic/README.md": {},
						"example_applications/basic/getting-started.md": {}
					}
				}
			],
			[
				"thumbnail",
				{
					"_index": 171,
					"title": {},
					"module": {},
					"group": {},
					"body": {
						"example_applications/bookshop/book-list.md": {}
					}
				}
			],
			[
				"time",
				{
					"_index": 236,
					"title": {},
					"module": {},
					"group": {},
					"body": {
						"example_applications/bookshop/welcome.md": {}
					}
				}
			],
			[
				"tip",
				{
					"_index": 235,
					"title": {},
					"module": {},
					"group": {},
					"body": {
						"example_applications/bookshop/welcome.md": {}
					}
				}
			],
			[
				"titl",
				{
					"_index": 140,
					"title": {},
					"module": {},
					"group": {},
					"body": {
						"example_applications/bookshop/book-detail.md": {},
						"example_applications/bookshop/book-list.md": {},
						"example_applications/bookshop/search-filter.md": {},
						"example_applications/bookshop/store.md": {},
						"example_applications/bookshop/welcome.md": {}
					}
				}
			],
			[
				"toggl",
				{
					"_index": 237,
					"title": {},
					"module": {},
					"group": {},
					"body": {
						"example_applications/bookshop/welcome.md": {}
					}
				}
			],
			[
				"tooltip",
				{
					"_index": 93,
					"title": {},
					"module": {},
					"group": {},
					"body": {
						"example_applications/basic/advanced-topics.md": {}
					}
				}
			],
			[
				"top",
				{
					"_index": 187,
					"title": {},
					"module": {},
					"group": {},
					"body": {
						"example_applications/bookshop/search-filter.md": {},
						"example_applications/bookshop/store.md": {}
					}
				}
			],
			[
				"topic",
				{
					"_index": 28,
					"title": {
						"example_applications/basic/advanced-topics.md": {}
					},
					"module": {},
					"group": {},
					"body": {
						"example_applications/basic/README.md": {},
						"example_applications/basic/advanced-topics.md": {},
						"example_applications/basic/getting-started.md": {}
					}
				}
			],
			[
				"transact",
				{
					"_index": 166,
					"title": {},
					"module": {},
					"group": {},
					"body": {
						"example_applications/bookshop/book-detail.md": {}
					}
				}
			],
			[
				"two",
				{
					"_index": 208,
					"title": {},
					"module": {},
					"group": {},
					"body": {
						"example_applications/bookshop/store.md": {}
					}
				}
			],
			[
				"unavail",
				{
					"_index": 179,
					"title": {},
					"module": {},
					"group": {},
					"body": {
						"example_applications/bookshop/book-list.md": {},
						"example_applications/bookshop/store.md": {}
					}
				}
			],
			[
				"upcom",
				{
					"_index": 86,
					"title": {},
					"module": {},
					"group": {},
					"body": {
						"example_applications/basic/advanced-topics.md": {}
					}
				}
			],
			[
				"updat",
				{
					"_index": 79,
					"title": {},
					"module": {},
					"group": {},
					"body": {
						"example_applications/basic/advanced-topics.md": {},
						"example_applications/bookshop/search-filter.md": {}
					}
				}
			],
			[
				"url",
				{
					"_index": 82,
					"title": {},
					"module": {},
					"group": {},
					"body": {
						"example_applications/basic/advanced-topics.md": {},
						"example_applications/basic/getting-started.md": {}
					}
				}
			],
			[
				"us",
				{
					"_index": 180,
					"title": {},
					"module": {},
					"group": {},
					"body": {
						"example_applications/bookshop/book-list.md": {},
						"example_applications/bookshop/store.md": {}
					}
				}
			],
			[
				"usag",
				{
					"_index": 60,
					"title": {},
					"module": {},
					"group": {},
					"body": {
						"example_applications/basic/advanced-topics.md": {}
					}
				}
			],
			[
				"usd",
				{
					"_index": 211,
					"title": {},
					"module": {},
					"group": {},
					"body": {
						"example_applications/bookshop/store.md": {}
					}
				}
			],
			[
				"version",
				{
					"_index": 204,
					"title": {},
					"module": {},
					"group": {},
					"body": {
						"example_applications/bookshop/search-filter.md": {}
					}
				}
			],
			[
				"via",
				{
					"_index": 71,
					"title": {},
					"module": {},
					"group": {},
					"body": {
						"example_applications/basic/advanced-topics.md": {}
					}
				}
			],
			[
				"view",
				{
					"_index": 50,
					"title": {},
					"module": {},
					"group": {},
					"body": {
						"example_applications/basic/README.md": {},
						"example_applications/bookshop/book-detail.md": {},
						"example_applications/bookshop/book-list.md": {},
						"example_applications/bookshop/store.md": {},
						"example_applications/bookshop/welcome.md": {}
					}
				}
			],
			[
				"viewer",
				{
					"_index": 9,
					"title": {},
					"module": {},
					"group": {},
					"body": {
						"example_applications/basic/README.md": {}
					}
				}
			],
			[
				"visit",
				{
					"_index": 126,
					"title": {},
					"module": {},
					"group": {},
					"body": {
						"example_applications/basic/getting-started.md": {}
					}
				}
			],
			[
				"walk",
				{
					"_index": 109,
					"title": {},
					"module": {},
					"group": {},
					"body": {
						"example_applications/basic/getting-started.md": {}
					}
				}
			],
			[
				"welcom",
				{
					"_index": 5,
					"title": {
						"example_applications/bookshop/welcome.md": {}
					},
					"module": {},
					"group": {},
					"body": {
						"example_applications/basic/README.md": {},
						"example_applications/bookshop/welcome.md": {}
					}
				}
			],
			[
				"whether",
				{
					"_index": 153,
					"title": {},
					"module": {},
					"group": {},
					"body": {
						"example_applications/bookshop/book-detail.md": {},
						"example_applications/bookshop/book-list.md": {}
					}
				}
			],
			[
				"without",
				{
					"_index": 38,
					"title": {},
					"module": {},
					"group": {},
					"body": {
						"example_applications/basic/README.md": {}
					}
				}
			],
			[
				"work",
				{
					"_index": 201,
					"title": {},
					"module": {},
					"group": {},
					"body": {
						"example_applications/bookshop/search-filter.md": {}
					}
				}
			]
		],
		"pipeline": [
			"stemmer"
		]
	},
	"Documents": {
		"example_applications/basic/README.md": {
			"Title": "Inline Documentation Example",
			"Module": "basic",
			"Group": "example_applications",
			"DocPath": "README.md"
		},
		"example_applications/basic/advanced-topics.md": {
			"Title": "Advanced Topics",
			"Module": "basic",
			"Group": "example_applications",
			"DocPath": "advanced-topics.md"
		},
		"example_applications/basic/getting-started.md": {
			"Title": "Getting Started",
			"Module": "basic",
			"Group": "example_applications",
			"DocPath": "getting-started.md"
		},
		"example_applications/bookshop/book-detail.md": {
			"Title": "Book Details & Purchasing",
			"Module": "bookshop",
			"Group": "example_applications",
			"DocPath": "book-detail.md"
		},
		"example_applications/bookshop/book-list.md": {
			"Title": "Browsing the Book Catalog",
			"Module": "bookshop",
			"Group": "example_applications",
			"DocPath": "book-list.md"
		},
		"example_applications/bookshop/search-filter.md": {
			"Title": "Searching & Filtering",
			"Module": "bookshop",
			"Group": "example_applications",
			"DocPath": "search-filter.md"
		},
		"example_applications/bookshop/store.md": {
			"Title": "The Store Page",
			"Module": "bookshop",
			"Group": "example_applications",
			"DocPath": "store.md"
		},
		"example_applications/bookshop/welcome.md": {
			"Title": "Welcome to the Bookshop",
			"Module": "bookshop",
			"Group": "example_applications",
			"DocPath": "welcome.md"
		}
	}
}